MANIFEST.in
README.md
setup.py
nlptools/__init__.py
nlptools.egg-info/PKG-INFO
nlptools.egg-info/SOURCES.txt
nlptools.egg-info/dependency_links.txt
nlptools.egg-info/entry_points.txt
nlptools.egg-info/requires.txt
nlptools.egg-info/top_level.txt
nlptools/commands/__init__.py
nlptools/commands/cleaner.py
nlptools/commands/feature_tfidf_py3.py
nlptools/commands/get_raw_tweets.py
nlptools/commands/get_url.py
nlptools/commands/lemmatizer_nltk_py3.py
nlptools/commands/stemmer_nltk_py3.py
nlptools/commands/tokenizer_nltk_py3.py