Metadata-Version: 1.1
Name: nlptools
Version: 0.5.1
Summary: Unix inspired utilities for Natural Language Processing
Home-page: https://github.com/jepemo/nlptools
Author: Jeremies Pérez Morata
Author-email: jeremiespm@gmail.com
License: GPL-v3
Keywords: NLP,CL,natural language processing,computational linguistics,parsing,tagging,tokenizing,syntax,linguistics,language,natural language,text analytics,linux command
Platform: UNKNOWN
Classifier: Development Status :: 4 - Beta
Classifier: Intended Audience :: Developers
Classifier: Topic :: Text Processing
Classifier: Topic :: Text Processing :: Filters
Classifier: Topic :: Text Processing :: General
Classifier: Topic :: Text Processing :: Indexing
Classifier: Topic :: Text Processing :: Linguistic
Classifier: License :: OSI Approved :: GNU General Public License v3 (GPLv3)
Classifier: Programming Language :: Python :: 3
Classifier: Programming Language :: Python :: 3.3
Classifier: Programming Language :: Python :: 3.4
Classifier: Programming Language :: Python :: 3.5
Classifier: Programming Language :: Python :: 3.6
